{
  "loginConfig": {
    "greetingL10n": "WebTrit",
    "modeSelectActions": [
      {
        "enabled": true,
        "type": "login",
        "titleL10n": "login_Button_signUpToDemoInstance",
        "isLaunchButtonVisible": true
      },
      {
        "enabled": false,
        "embeddedId": 1,
        "type": "embedded",
        "titleL10n": "login_Button_signIn",
        "isLaunchButtonVisible": false
      }
    ]
  },
  "mainConfig": {
    "bottomMenu": {
      "cacheSelectedTab": true,
      "tabs": [
        {
          "enabled": true,
          "initial": false,
          "type": "favorites",
          "titleL10n": "main_BottomNavigationBarItemLabel_favorites",
          "icon": "0xe5fd"
        },
        {
          "enabled": true,
          "initial": false,
          "type": "recents",
          "titleL10n": "main_BottomNavigationBarItemLabel_recents",
          "icon": "0xe03a"
        },
        {
          "enabled": true,
          "initial": false,
          "type": "contacts",
          "titleL10n": "main_BottomNavigationBarItemLabel_contacts",
          "icon": "0xee35",
          "contactSourceTypes": [
            "local",
            "external"
          ]
        },
        {
          "enabled": true,
          "initial": true,
          "type": "keypad",
          "titleL10n": "main_BottomNavigationBarItemLabel_keypad",
          "icon": "0xe1ce"
        },
        {
          "enabled": true,
          "initial": false,
          "type": "messaging",
          "titleL10n": "main_BottomNavigationBarItemLabel_chats",
          "icon": "0xe155"
        },
        {
          "enabled": false,
          "initial": false,
          "type": "embedded",
          "titleL10n": "main_BottomNavigationBarItemLabel_embedded",
          "icon": "0xe2ce",
          "embeddedResourceId": 2
        }
      ]
    },
    "systemNotificationsEnabled": true
  },
  "settingsConfig": {
    "sections": [
      {
        "titleL10n": "settings_ListViewTileTitle_features",
        "enabled": false,
        "items": [
          {
            "enabled": false,
            "type": "voicemail",
            "titleL10n": "settings_ListViewTileTitle_voicemail",
            "icon": "0xe6c1"
          }
        ]
      },
      {
        "titleL10n": "settings_ListViewTileTitle_settings",
        "enabled": true,
        "items": [
          {
            "enabled": true,
            "type": "network",
            "titleL10n": "settings_ListViewTileTitle_network",
            "icon": "0xe424"
          },
          {
            "enabled": true,
            "type": "mediaSettings",
            "titleL10n": "settings_ListViewTileTitle_mediaSettings",
            "icon": "0xf1cf"
          },
          {
            "enabled": true,
            "type": "callerId",
            "titleL10n": "settings_ListViewTileTitle_callerId",
            "icon": "0xf26e"
          },
          {
            "enabled": true,
            "type": "language",
            "titleL10n": "settings_ListViewTileTitle_language",
            "icon": "0xe366"
          },
          {
            "enabled": false,
            "type": "help",
            "titleL10n": "settings_ListViewTileTitle_help",
            "icon": "0xe30b"
          },
          {
            "enabled": true,
            "type": "terms",
            "titleL10n": "settings_ListViewTileTitle_termsConditions",
            "icon": "0xeedf",
            "embeddedResourceId": 4
          },
          {
            "enabled": true,
            "type": "about",
            "titleL10n": "settings_ListViewTileTitle_about",
            "icon": "0xe140"
          }
        ]
      },
      {
        "titleL10n": "settings_ListViewTileTitle_toolbox",
        "enabled": true,
        "items": [
          {
            "enabled": true,
            "titleL10n": "settings_ListViewTileTitle_logRecordsConsole",
            "icon": "0xee79",
            "type": "log"
          },
          {
            "enabled": true,
            "type": "selfConfig",
            "titleL10n": "settings_ListViewTileTitle_self_config",
            "icon": "0xef7a"
          },
          {
            "enabled": true,
            "titleL10n": "settings_ListViewTileTitle_accountDelete",
            "icon": "0xe1bb",
            "type": "deleteAccount"
          },
          {
            "enabled": false,
            "titleL10n": "settings_ListViewTileTitle_embedded1",
            "icon": "0xe3a2",
            "type": "embedded",
            "embeddedResourceId": 5
          },
          {
            "enabled": false,
            "titleL10n": "settings_ListViewTileTitle_embedded2",
            "icon": "0xe3a2",
            "type": "embedded",
            "embeddedResourceId": 6
          }
        ]
      },
      {
        "titleL10n": "settings_ListViewTileTitle_embedded_section1",
        "enabled": false,
        "items": [
          {
            "enabled": true,
            "titleL10n": "settings_ListViewTileTitle_embedded3",
            "icon": "0xe3a2",
            "type": "embedded",
            "embeddedResourceId": 7
          }
        ]
      }
    ]
  },
  "callConfig": {
    "videoEnabled": true,
    "transfer": {
      "enableBlindTransfer": true,
      "enableAttendedTransfer": true
    },
    "encoding": {
      "bypassConfig": false,
      "__defaultPresetOverride": {
        "audioBitrate": 56,
        "videoBitrate": 512,
        "ptime": 20,
        "maxptime": 80,
        "opusSamplingRate": 24000,
        "opusBitrate": 16,
        "opusStereo": false,
        "opusDtx": true
      }
    },
    "peerConnection": {
      "negotiation": {
        "includeInactiveVideoInOfferAnswer": false
      }
    }
  },
  "embeddedResources": [
    {
      "id": 1,
      "uri": "https://webtrit-app.web.app/example/example_embedded_login.html",
      "toolbar": {
        "showToolbar": true,
        "titleL10n": "login_requestCredentials_title"
      }
    },
    {
      "id": 2,
      "uri": "https://webtrit-app.web.app/example/example_embedded_payload_data.html",
      "payload": [
        "coreToken"
      ],
      "toolbar": {
        "showToolbar": false
      }
    },
    {
      "id": 3,
      "uri": "https://webtrit-app.web.app/example/example_embedded_call.html",
      "toolbar": {
        "showToolbar": false
      }
    },
    {
      "id": 4,
      "uri": "https://webtrit.com/legal/privacy-policy-for-webtrit-app/",
      "type": "terms",
      "toolbar": {
        "showToolbar": true,
        "titleL10n": "settings_ListViewTileTitle_termsConditions"
      }
    },
    {
      "id": 5,
      "uri": "https://webtrit-app.web.app/example/example_embedded_registration.html",
      "toolbar": {
        "showToolbar": true,
        "titleL10n": "login_requestCredentials_title"
      }
    },
    {
      "id": 6,
      "uri": "https://webtrit-app.web.app/example/example_embedded_statistics.html",
      "toolbar": {
        "showToolbar": true,
        "titleL10n": "login_requestCredentials_title"
      }
    },
    {
      "id": 7,
      "uri": "https://webtrit-app.web.app/example/example_embedded_rating.html",
      "toolbar": {
        "showToolbar": true,
        "titleL10n": "login_requestCredentials_title"
      }
    }
  ]
}
